{"type": "Feature", "id": 28752278, "geometry": {"type": "Point", "coordinates": [101.708107, 2.75846]}, "properties": {"woe:id": 28752278, "woe:parent_id": 1147233, "woe:name": "Kuala Lumpur International Airport", "woe:placetype": 14, "woe:placetype_name": "Airport", "woe:lang": "ENG", "iso:country": "MY", "meta:provider": ["geoplanet:7.3.1", "geoplanet:7.3.2", "geoplanet:7.4.0", "geoplanet:7.4.1", "geoplanet:7.5.1", "geoplanet:7.5.2", "geoplanet:7.6.0", "geoplanet:7.8.1", "geoplanet:7.9.0", "geoplanet:7.10.0", "geoplanet:8.0.0", "woeplanet:8.0.0"], "meta:indexed": "2020-08-20T20:26:06.696956", "woe:alias_UNK_V": ["Klia Int'l Airport"], "woe:alias_ENG_V": ["KUL", "KUL Airport", "K L International Airport"], "meta:updated": "2020-10-14T12:13:07.715840", "woe:alias_ENG_A": ["KLIA"], "woe:hierarchy": {"continent": 24865671, "country": 23424901, "town": 0, "planet": 1, "county": 56013573, "suburb": 0, "state": 2346306, "region": 0, "localadmin": 56013862}, "woe:timezone_id": 56043603, "woe:hash": "w22rdqjt4wjq", "woe:centroid": [101.708107, 2.75846], "geom:latitude": 2.75846, "geom:longitude": 101.708107, "geom:hash": "w22rdqjt4wjq", "woe:latitude": 2.75846, "geom:centroid": [101.708107, 2.75846], "woe:longitude": 101.708107, "woe:repo": "woeplanet-airport-my", "geom:area": 0.0, "woe:scale": 19}}